ab/__init__.py
ab/chatprep/__init__.py
ab/chatprep/consts.py
ab/chatprep/example_builder.py
ab/chatprep/prompt_builder.py
ab/chatprep/renderer.py
ab/chatprep/schema.py
ab/chatprep/validate.py
ab/chatprep/cli/__init__.py
ab/chatprep/cli/main.py
ab/chatprep/detectors/__init__.py
ab/chatprep/detectors/ast_signals.py
ab/chatprep/utils/__init__.py
ab/chatprep/utils/code_io.py
ab/chatprep/utils/manifest.py
ab/chatprep/utils/split_utils.py
ab/chatprep/utils/validator.py
ab/dup/__init__.py
ab/dup/main.py
ab/dup/preprocessing.py
ab/dup/consts/__init__.py
ab/dup/consts/settings.py
ab/dup/utils/__init__.py
ab/dup/utils/astfp.py
ab/dup/utils/family.py
ab/dup/utils/hashing.py
ab/dup/utils/io_utils.py
ab/dup/utils/logutils.py
ab/dup/utils/lsh.py
ab/dup/utils/prefix.py
ab/dup/utils/report.py
ab/dup/utils/textproc.py
nn_dup-2.2.4.dist-info/licenses/LICENSE
nn_dup-2.2.4.dist-info/METADATA
nn_dup-2.2.4.dist-info/WHEEL
nn_dup-2.2.4.dist-info/entry_points.txt
nn_dup-2.2.4.dist-info/top_level.txt
nn_dup-2.2.4.dist-info/RECORD
