Metadata-Version: 2.4
Name: nn-dup
Version: 2.2.4
Summary: Prefix-aware curation & near-dedup for NN code via MinHash/LSH and AST fingerprints.
Author-email: ABrain One and contributors <AI@ABrain.one>
License: MIT License
Project-URL: Homepage, https://ABrain.one
Project-URL: Repository, https://github.com/ABrain-One/nn-dup
Project-URL: Bug Tracker, https://github.com/ABrain-One/nn-dup/issues
Keywords: LLM,deduplication,MinHash,LSH,AST,neural networks,data curation,pretraining,fine-tuning
Classifier: Programming Language :: Python :: 3
Classifier: License :: OSI Approved :: MIT License
Classifier: Operating System :: OS Independent
Classifier: Topic :: Scientific/Engineering :: Artificial Intelligence
Classifier: Topic :: Software Development :: Code Generators
Requires-Python: >=3.10
License-File: LICENSE
Requires-Dist: nn-dataset>=2.1.0
Requires-Dist: datasketch
Requires-Dist: pandas<3.0,>=1.3
Requires-Dist: tqdm
Provides-Extra: dev
Requires-Dist: black>=23.0; extra == "dev"
Requires-Dist: isort>=5.0; extra == "dev"
Requires-Dist: flake8>=6.0; extra == "dev"
Dynamic: license-file
